palje/__init__.py
palje/cli.py
palje/cli2.py
palje/db_to_confluence.py
palje/progress_tracker.py
palje/version.py
palje/cli_commands/copy_cmd.py
palje/cli_commands/delete_cmd.py
palje/cli_commands/document_cmd.py
palje/cli_commands/sort_cmd.py
palje/confluence/confluence_models.py
palje/confluence/confluence_ops.py
palje/confluence/confluence_rest.py
palje/confluence/confluence_rest_models.py
palje/confluence/confluence_types.py
palje/confluence/storage_format.py
palje/confluence/utils.py
palje/confluence/xml_handling.py
palje/gui/gui.py
palje/gui/palje.png
palje/gui/components/confluence_connection_widget.py
palje/gui/components/db_browser_widget.py
palje/gui/components/db_server_widget.py
palje/mssql/database_queries.ini
palje/mssql/mssql_database.py
palje-3.0.0.dist-info/LICENSE
palje-3.0.0.dist-info/METADATA
palje-3.0.0.dist-info/WHEEL
palje-3.0.0.dist-info/entry_points.txt
palje-3.0.0.dist-info/top_level.txt
palje-3.0.0.dist-info/RECORD
