Metadata-Version: 2.2
Name: palje
Version: 3.0.0
Summary: A tool for creating hierarchical documentation of SQL Server databases to Confluence wiki.
Author: ALM Partners Oy
Maintainer: ALM Partners Oy
License:                                  Apache License
Project-URL: Repository, https://github.com/ALMPartners/palje
Keywords: palje
Classifier: Intended Audience :: Developers
Classifier: License :: OSI Approved :: Apache Software License
Classifier: Topic :: Database
Classifier: Topic :: Documentation
Classifier: Programming Language :: Python :: 3.11
Classifier: Programming Language :: Python :: 3.12
Classifier: Programming Language :: Python :: 3.13
Requires-Python: >=3.11
License-File: LICENSE
Requires-Dist: azure-identity~=1.14
Requires-Dist: pyodbc~=5.2
Requires-Dist: aiohttp~=3.9
Requires-Dist: click~=8.1
Requires-Dist: lxml~=5.3
Requires-Dist: aiofile~=3.8
Provides-Extra: dev
Requires-Dist: black~=24.8; extra == "dev"
Requires-Dist: pre-commit~=3.7; extra == "dev"
Provides-Extra: test
Requires-Dist: tox~=4.15; extra == "test"
Requires-Dist: pytest-aiohttp~=1.0; extra == "test"
Requires-Dist: sqlalchemy[mssql]~=2.0.29; extra == "test"
Requires-Dist: ahjo~=3.10.0; extra == "test"
Provides-Extra: msibuild
Requires-Dist: cx_freeze~=7.0; extra == "msibuild"
